{
  "users": [
    {
      "name": "Vipin",
      "email": "vipin@gmail.com",
      "password": "admin",
      "id": 1
    },
    {
      "name": "Vipin Kumar",
      "email": "vipins@gmail.com",
      "password": "admin",
      "id": 2
    },
    {
      "name": "abc",
      "email": "abc@gmail.com",
      "password": "admin",
      "id": 3
    },
    {
      "name": "abcd",
      "email": "abcd@gmail.com",
      "password": "admin",
      "id": 4
    },
    {
      "name": "abc",
      "email": "abcde@gmail.com",
      "password": "admin",
      "id": 5
    },
    {
      "name": "abcdef",
      "email": "abcdef@gmail.com",
      "password": "adminf",
      "id": 6
    },
    {
      "name": "Vipin",
      "email": "vipink28@gmail.com",
      "password": "admin",
      "id": 7
    },
    {
      "name": "abcedg",
      "email": "abcdfge@gmail.com",
      "password": "admin",
      "id": 8
    },
    {
      "name": "Vipin",
      "email": "vipinkumar@gmail.com",
      "password": "admin",
      "id": 9
    },
    {
      "name": "ishu",
      "email": "ishu@gmail.com",
      "password": "admin",
      "id": 10
    }
  ],
  "tasks": []
}